iiif_prezi3/__init__.py
iiif_prezi3/base.py
iiif_prezi3/loader.py
iiif_prezi3/skeleton.py
iiif_prezi3/config/__init__.py
iiif_prezi3/config/config.py
iiif_prezi3/config/extensions.json
iiif_prezi3/extensions/__init__.py
iiif_prezi3/extensions/example_extension.py
iiif_prezi3/helpers/__init__.py
iiif_prezi3/helpers/add_image.py
iiif_prezi3/helpers/add_item.py
iiif_prezi3/helpers/add_label.py
iiif_prezi3/helpers/add_metadata.py
iiif_prezi3/helpers/add_range.py
iiif_prezi3/helpers/add_service.py
iiif_prezi3/helpers/add_thumbnail.py
iiif_prezi3/helpers/annotation_helpers.py
iiif_prezi3/helpers/auto_fields.py
iiif_prezi3/helpers/canvas_sizes.py
iiif_prezi3/helpers/create_canvas_from_iiif.py
iiif_prezi3/helpers/make_canvas.py
iiif_prezi3/helpers/make_collection.py
iiif_prezi3/helpers/make_manifest.py
iiif_prezi3/helpers/make_range.py
iiif_prezi3/helpers/make_service.py
iiif_prezi3/helpers/set_hwd.py
iiif_prezi3/helpers/set_hwd_from_file.py
iiif_prezi3/helpers/set_hwd_from_iiif.py
iiif_prezi3/helpers/to_reference.py
iiif_prezi3-3.1.0.dist-info/licenses/LICENSE
iiif_prezi3-3.1.0.dist-info/METADATA
iiif_prezi3-3.1.0.dist-info/WHEEL
iiif_prezi3-3.1.0.dist-info/top_level.txt
iiif_prezi3-3.1.0.dist-info/RECORD
