Metadata-Version: 2.4
Name: iiif-prezi3
Version: 3.1.0
Summary: IIIF Presentation v3 API implementation
Home-page: https://github.com/iiif-prezi/iiif-prezi3
Author: IIIF Prezi3 Team
License: Apache License, Version 2.0
Classifier: Development Status :: 5 - Production/Stable
Classifier: Intended Audience :: Developers
Classifier: License :: OSI Approved :: Apache Software License
Classifier: Operating System :: OS Independent
Classifier: Programming Language :: Python
Classifier: Programming Language :: Python :: 3
Classifier: Programming Language :: Python :: 3.9
Classifier: Programming Language :: Python :: 3.10
Classifier: Programming Language :: Python :: 3.11
Classifier: Programming Language :: Python :: 3.12
Classifier: Programming Language :: Python :: 3.13
Classifier: Topic :: Internet :: WWW/HTTP
Classifier: Topic :: Multimedia :: Graphics :: Graphics Conversion
Classifier: Topic :: Software Development :: Libraries :: Python Modules
Classifier: Environment :: Web Environment
Requires-Python: >=3
License-File: LICENSE
Requires-Dist: pydantic<3.0.0,>=2.0.0
Requires-Dist: requests<3.0.0,>=2.28.0
Requires-Dist: Pillow<=12.0.0,>=9.1.1
Provides-Extra: docs
Requires-Dist: mkdocs<2.0.0,>=1.4.0; extra == "docs"
Requires-Dist: mkdocs-material<10.0.0,>=8.0.0; extra == "docs"
Requires-Dist: mkdocstrings-python<2.0.0,>=0.7.0; extra == "docs"
Requires-Dist: griffe<2.0.0,>=0.25.2; extra == "docs"
Requires-Dist: mkdocs-awesome-pages-plugin<3.0.0,>=2.8.0; extra == "docs"
Provides-Extra: dev
Requires-Dist: autopep8<3.0.0,>=1.6.0; extra == "dev"
Requires-Dist: isort<6.0.0,>=5.10.1; extra == "dev"
Requires-Dist: flake8<8.0.0,>=7.2.0; extra == "dev"
Requires-Dist: flake8-docstrings<2.0.0,>=1.6.0; extra == "dev"
Requires-Dist: flake8-isort<7.0.0,>=4.1.1; extra == "dev"
Requires-Dist: tox<5.0.0,>=3.25.0; extra == "dev"
Requires-Dist: Pillow<=12.0.0,>=9.1.1; extra == "dev"
Requires-Dist: deepdiff<9.0.0,>=6.2.2; extra == "dev"
Requires-Dist: datamodel-code-generator<1.0.0,>=0.17.1; extra == "dev"
Dynamic: author
Dynamic: classifier
Dynamic: description
Dynamic: description-content-type
Dynamic: home-page
Dynamic: license
Dynamic: license-file
Dynamic: provides-extra
Dynamic: requires-dist
Dynamic: requires-python
Dynamic: summary
